ibflex/Types.py
ibflex/__init__.py
ibflex/__version__.py
ibflex/client.py
ibflex/enums.py
ibflex/parser.py
ibflex/py.typed
ibflex/utils.py
ibflex2-1.0.0.dist-info/licenses/LICENSE.txt
ibflex2-1.0.0.dist-info/METADATA
ibflex2-1.0.0.dist-info/WHEEL
ibflex2-1.0.0.dist-info/entry_points.txt
ibflex2-1.0.0.dist-info/top_level.txt
ibflex2-1.0.0.dist-info/RECORD
